borica/__init__.py
borica/base.py
borica/config.py
borica/exceptions.py
borica/request.py
borica/response.py
borica_py-0.0.0.dist-info/LICENSE
borica_py-0.0.0.dist-info/METADATA
borica_py-0.0.0.dist-info/WHEEL
borica_py-0.0.0.dist-info/top_level.txt
borica_py-0.0.0.dist-info/RECORD
