Metadata-Version: 2.1
Name: borica-py
Version: 0.0.0
Summary: Python integration for Borica based payments
Home-page: UNKNOWN
Author: CodeBrew
Author-email: contact@codebrew.io
License: MIT
Platform: UNKNOWN
Requires-Python: >=3.7
Requires-Dist: pyOpenSSL (==20.0.*)
